grader_convert/__init__.py
grader_convert/_version.py
grader_convert/grader-config.py
grader_convert/main.py
grader_convert/utils.py
grader_convert/validator.py
grader_convert/converters/__init__.py
grader_convert/converters/autograde.py
grader_convert/converters/base.py
grader_convert/converters/baseapp.py
grader_convert/converters/generate_assignment.py
grader_convert/converters/generate_feedback.py
grader_convert/converters/generate_solution.py
grader_convert/converters/updateapp.py
grader_convert/converters/validateapp.py
grader_convert/gradebook/__init__.py
grader_convert/gradebook/gradebook.py
grader_convert/gradebook/models.py
grader_convert/nbgraderformat/__init__.py
grader_convert/nbgraderformat/common.py
grader_convert/nbgraderformat/v1.json
grader_convert/nbgraderformat/v1.py
grader_convert/nbgraderformat/v2.json
grader_convert/nbgraderformat/v2.py
grader_convert/nbgraderformat/v3.json
grader_convert/nbgraderformat/v3.py
grader_convert/preprocessors/__init__.py
grader_convert/preprocessors/addrevert.py
grader_convert/preprocessors/base.py
grader_convert/preprocessors/checkcellmetadata.py
grader_convert/preprocessors/clearalwayshiddentests.py
grader_convert/preprocessors/clearhiddentests.py
grader_convert/preprocessors/clearmarkingscheme.py
grader_convert/preprocessors/clearoutput.py
grader_convert/preprocessors/clearsolutions.py
grader_convert/preprocessors/computechecksums.py
grader_convert/preprocessors/deduplicateids.py
grader_convert/preprocessors/execute.py
grader_convert/preprocessors/getgrades.py
grader_convert/preprocessors/headerfooter.py
grader_convert/preprocessors/limitoutput.py
grader_convert/preprocessors/lockcells.py
grader_convert/preprocessors/overwritecells.py
grader_convert/preprocessors/overwritekernelspec.py
grader_convert/preprocessors/saveautogrades.py
grader_convert/preprocessors/savecells.py
grader_convert/templates/config/grader_config.py
grader_convert/templates/feedback/conf.json
grader_convert/templates/feedback/index.html.j2
grader_convert-0.2.3.dist-info/METADATA
grader_convert-0.2.3.dist-info/WHEEL
grader_convert-0.2.3.dist-info/entry_points.txt
grader_convert-0.2.3.dist-info/top_level.txt
grader_convert-0.2.3.dist-info/RECORD
