Metadata-Version: 2.1
Name: grader-convert
Version: 0.2.3
Summary: Grader convert
Author: Florian Jäger, Matthias Matt
License: BSD-3-Clause
Project-URL: Homepage, https://github.com/TU-Wien-dataLAB/Grader-Service
Project-URL: Repository, https://github.com/TU-Wien-dataLAB/Grader-Service
Project-URL: Documentation, https://grader-service.readthedocs.io/en/latest/index.html
Classifier: License :: OSI Approved :: BSD License
Classifier: Development Status :: 3 - Alpha
Classifier: Framework :: Jupyter
Classifier: Programming Language :: Python :: 3
Classifier: Programming Language :: Python :: 3.8
Classifier: Programming Language :: Python :: 3.9
Classifier: Programming Language :: Python :: 3.10
Requires-Python: >=3.8
Requires-Dist: jupyter-core >=4.7.1
Requires-Dist: jsonschema >=3.2.0
Requires-Dist: nbformat >=5.4.0
Requires-Dist: tornado >=6.2
Requires-Dist: SQLAlchemy >=1.4.22
Requires-Dist: pytest >=6.2.4
Requires-Dist: traitlets >=5.1.1
Requires-Dist: python-dateutil >=2.8.2
Requires-Dist: jupyter-client >=7.1.1
Requires-Dist: nbconvert >=6.4.0
